[
  {
    "first_name": "Linda",
    "last_name": "Moore",
    "name": "Linda Moore",
    "email": "linda.moore0@example.com",
    "status": "active",
    "priviledges": "member",
    "company": "phg",
    "user_id": "fcb274fa-c0d8-465a-a76f-eddec2bcceff"
  },
  {
    "first_name": "Michael",
    "last_name": "Smith",
    "name": "Michael Smith",
    "email": "michael.smith1@example.com",
    "status": "active",
    "priviledges": "member",
    "company": "phg",
    "user_id": "08b668a2-fa2a-47ab-b02b-016203d000d9"
  },
  {
    "first_name": "William",
    "last_name": "Moore",
    "name": "William Moore",
    "email": "william.moore2@example.com",
    "status": "active",
    "priviledges": "member",
    "company": "phg",
    "user_id": "d2dfd989-baa8-4545-b355-47ac60b7643c"
  },
  {
    "first_name": "James",
    "last_name": "Miller",
    "name": "James Miller",
    "email": "james.miller3@example.com",
    "status": "active",
    "priviledges": "member",
    "company": "phg",
    "user_id": "91e6561c-6ced-4ed4-aab8-77b8831afebd"
  },
  {
    "first_name": "William",
    "last_name": "Jones",
    "name": "William Jones",
    "email": "william.jones4@example.com",
    "status": "active",
    "priviledges": "member",
    "company": "phg",
    "user_id": "60874da7-4721-4406-ba2d-ecad6ace765f"
  },
  {
    "first_name": "Mary",
    "last_name": "Wilson",
    "name": "Mary Wilson",
    "email": "mary.wilson5@example.com",
    "status": "active",
    "priviledges": "member",
    "company": "phg",
    "user_id": "7626f651-cee2-4ead-ab84-f4ac8d3c0551"
  },
  {
    "first_name": "John",
    "last_name": "Wilson",
    "name": "John Wilson",
    "email": "john.wilson6@example.com",
    "status": "active",
    "priviledges": "member",
    "company": "phg",
    "user_id": "ef99269d-05cd-44ba-be61-688cb7c82d60"
  },
  {
    "first_name": "Patricia",
    "last_name": "Miller",
    "name": "Patricia Miller",
    "email": "patricia.miller7@example.com",
    "status": "active",
    "priviledges": "member",
    "company": "phg",
    "user_id": "9d7ff25e-810e-4b58-afd7-0d681954dc7b"
  },
  {
    "first_name": "Linda",
    "last_name": "Brown",
    "name": "Linda Brown",
    "email": "linda.brown8@example.com",
    "status": "active",
    "priviledges": "member",
    "company": "phg",
    "user_id": "72d0ec21-902c-46f3-b5c0-c6a68087d2da"
  },
  {
    "first_name": "Michael",
    "last_name": "Wilson",
    "name": "Michael Wilson",
    "email": "michael.wilson9@example.com",
    "status": "active",
    "priviledges": "member",
    "company": "phg",
    "user_id": "a02b542d-0de0-4344-b755-2eeb4ea1b33f"
  }
 ]